dlt645/__init__.py
dlt645/common/__init__.py
dlt645/common/base_log.py
dlt645/common/env.py
dlt645/common/message_capture.py
dlt645/common/message_types.py
dlt645/common/transform.py
dlt645/config/demand_types.json
dlt645/config/energy_types.json
dlt645/config/event_record_types.json
dlt645/config/parameter_types.json
dlt645/config/variable_types.json
dlt645/model/__init__.py
dlt645/model/log.py
dlt645/model/validators.py
dlt645/model/data/__init__.py
dlt645/model/data/data_handler.py
dlt645/model/data/define/__init__.py
dlt645/model/data/define/demand_def.py
dlt645/model/data/define/energy_def.py
dlt645/model/data/define/event_record_def.py
dlt645/model/data/define/parameter_def.py
dlt645/model/data/define/variable_def.py
dlt645/model/types/__init__.py
dlt645/model/types/data_type.py
dlt645/model/types/dlt645_type.py
dlt645/protocol/__init__.py
dlt645/protocol/frame.py
dlt645/protocol/log.py
dlt645/protocol/protocol.py
dlt645/service/__init__.py
dlt645/service/clientsvc/__init__.py
dlt645/service/clientsvc/client_service.py
dlt645/service/clientsvc/log.py
dlt645/service/serversvc/__init__.py
dlt645/service/serversvc/log.py
dlt645/service/serversvc/server_service.py
dlt645/transport/__init__.py
dlt645/transport/client/__init__.py
dlt645/transport/client/log.py
dlt645/transport/client/rtu_client.py
dlt645/transport/client/tcp_client.py
dlt645/transport/server/__init__.py
dlt645/transport/server/log.py
dlt645/transport/server/rtu_server.py
dlt645/transport/server/tcp_server.py
dlt645-1.3.4.dist-info/METADATA
dlt645-1.3.4.dist-info/WHEEL
dlt645-1.3.4.dist-info/top_level.txt
dlt645-1.3.4.dist-info/RECORD
